pandora/__init__.py
pandora/client.py
pandora/clientbuilder.py
pandora/errors.py
pandora/transport.py
pandora/models/__init__.py
pandora/models/_base.py
pandora/models/ad.py
pandora/models/bookmark.py
pandora/models/playlist.py
pandora/models/search.py
pandora/models/station.py
pydora/__init__.py
pydora/audio_backend.py
pydora/configure.py
pydora/player.py
pydora/utils.py
pydora-2.3.1.dist-info/LICENSE.txt
pydora-2.3.1.dist-info/METADATA
pydora-2.3.1.dist-info/WHEEL
pydora-2.3.1.dist-info/entry_points.txt
pydora-2.3.1.dist-info/top_level.txt
pydora-2.3.1.dist-info/RECORD
